tkinterstylize
