Metadata-Version: 2.1
Name: tkinterstylize
Version: 0.0.5
Summary: Stylize Tkinter
Home-page: https://github.com/georgerahul24/tkinterstylize
Author: GR
Author-email: georgerahul24@gmail.com
License: MIT
Platform: UNKNOWN
License-File: LICENSE
